pyplot_xg/__init__.py
pyplot_xg/helpers.py
pyplot_xg-0.1.1.dist-info/licenses/LICENSE
pyplot_xg-0.1.1.dist-info/METADATA
pyplot_xg-0.1.1.dist-info/WHEEL
pyplot_xg-0.1.1.dist-info/top_level.txt
pyplot_xg-0.1.1.dist-info/RECORD
