Metadata-Version: 2.4
Name: pyplot_xg
Version: 0.1.1
Summary: Python package for plotting
Author-email: Xavier Gonzalez <haroldxaviergonzalez@gmail.com>
Requires-Python: >=3.9
License-File: LICENSE
Requires-Dist: matplotlib
Dynamic: license-file
